{
	"league": "Kreisliga Herren",
	"season": "2015/16",
	"start": "2000-01-01",
	"end": "2029-10-31",
	"teams": [ 
		{ "name": "Hachinger Kickers" },
		{ "name": "FC Miesbach"},
		{ "name": "Jahn München" },
		{ "name": "Weißblau Riem" },
		{ "name": "Shopping Queens PEP"},
		{ "name": "Eisbachsurfer" },
		{ "name": "Grillmeister vom Flaucher" },
		{ "name": "Fröttmaninger Fußballfans" },
		{ "name": "Leidgeprüfte 60er"},
		{ "name": "Tischkicker Neubiberg" },
		{ "name": "Gitarrengötter Giesing" },
		{ "name": "Latte Macchiato Mütter Haidhausen" },
		{ "name": "Bleifuß BMW" },
		{ "name": "JWD Freimann" },
		{ "name": "Olchinger Olme" },
		{ "name": "Frischauf Freising"},
		{ "name": "P.A. Sing" },
		{ "name": "Bogenhausener Bananenflanker" },
		{ "name": "Flachmänner vom Flaucher" },
		{ "name": "Isarritter"},
		{ "name": "Kegelklub von umme Ecke" },
		{ "name": "Team rot" },
		{ "name": "Lieber Scrum als Fußball" },
		{ "name": "Product Owner United"},
		{ "name": "Scrum Masters" },
		{ "name": "Rate limited Kanban" },
		{ "name": "Burndown-Brüder" },
		{ "name": "Die Storypoints"},
		{ "name": "Sprinter" },
		{ "name": "Release-Rocker" },
		{ "name": "PHP-Proleten"},
		{ "name": "Pythonistas" },
		{ "name": "Microsofties Unterhaching" },
		{ "name": "Pentium-Power" },
		{ "name": "Team Foobar"},
		{ "name": "Debugger Duisburg" },
		{ "name": "Truderinger Tastenquäler" },
		{ "name": "Team Blau" }
	]
}